sevenseg/__init__.py
sevenseg/sevenseg.py
micropython_sevenseg-1.1.0.dist-info/LICENSE
micropython_sevenseg-1.1.0.dist-info/METADATA
micropython_sevenseg-1.1.0.dist-info/WHEEL
micropython_sevenseg-1.1.0.dist-info/top_level.txt
micropython_sevenseg-1.1.0.dist-info/RECORD
