Metadata-Version: 2.1
Name: micropython_sevenseg
Version: 1.1.0
Summary: A simple MicroPython library for controlling 7-segment displays.
Home-page: https://github.com/kritishmohapatra/micropython-sevenseg
Author: Kritish Mohapatra
Author-email: kritishmohapatra06norisk@gmail.com
License: MIT
Classifier: Programming Language :: Python :: 3
Classifier: License :: OSI Approved :: MIT License
Classifier: Operating System :: OS Independent
License-File: LICENSE
